LICENSE
MANIFEST.in
README.md
requirements.txt
setup.py
uos_complex/__init__.py
uos_complex/workspace.py
uos_complex.egg-info/PKG-INFO
uos_complex.egg-info/SOURCES.txt
uos_complex.egg-info/dependency_links.txt
uos_complex.egg-info/requires.txt
uos_complex.egg-info/top_level.txt
uos_complex/core/__init__.py
uos_complex/core/objects.py
uos_complex/highorder/__init__.py
uos_complex/highorder/algorithm.py
uos_complex/highorder/dataset.py
uos_complex/highorder/metrics.py
uos_complex/percolation/__init__.py
uos_complex/util/__init__.py