Metadata-Version: 1.2
Name: uos-complex
Version: 0.1.1
Summary: Python library for complex system and network science lab of University of Seoul.
Home-page: UNKNOWN
Author: Jung-Hoon Jung
Author-email: jh.jung@uos.ac.kr
License: UNKNOWN
Platform: UNKNOWN
Requires-Python: >=3
